{"type": "Feature", "id": 12514587, "properties": {"woe:id": 12514587, "woe:parent_id": 475401, "woe:name": "Karmilava Airport", "woe:placetype": 14, "woe:placetype_name": "Airport", "woe:lang": "ENG", "iso:country": "LT", "meta:provider": ["geoplanet:7.3.1", "geoplanet:7.3.2", "geoplanet:7.4.0", "geoplanet:7.4.1", "geoplanet:7.5.1", "geoplanet:7.5.2", "geoplanet:7.6.0", "geoplanet:7.8.1", "geoplanet:7.9.0", "geoplanet:7.10.0", "geoplanet:8.0.0", "woeplanet:8.0.0"], "meta:indexed": "2020-08-20T20:58:42.501957", "woe:alias_ENG_V": ["KUN Airport", "KUN", "Karmilava"], "meta:updated": "2020-08-22T01:58:39.667274", "woe:hierarchy": {"continent": 24865675, "country": 23424875, "town": 0, "planet": 1, "county": 2346057, "suburb": 0, "state": 55848084, "region": 0, "localadmin": 56043951}, "woe:timezone_id": 28350922, "woe:hash": "u9c0g3cw3t7m", "woe:centroid": [24.051201, 54.986301], "geom:latitude": 54.986301, "geom:longitude": 24.051201, "geom:hash": "u9c0g3cw3t7m", "woe:latitude": 54.986301, "geom:centroid": [24.051201, 54.986301], "woe:longitude": 24.051201, "woe:repo": "woeplanet-airport-lt"}, "geometry": {"coordinates": [24.051201, 54.986301], "type": "Point"}}